fabazon/__init__.py
fabazon/ec2.py
fabazon/elb.py
fabazon/roles.py
fabazon/s3.py
fabazon-0.3.1.dist-info/METADATA
fabazon-0.3.1.dist-info/RECORD
fabazon-0.3.1.dist-info/WHEEL
fabazon-0.3.1.dist-info/top_level.txt
