Metadata-Version: 2.1
Name: fabazon
Version: 0.3.1
Summary: Utilities for interfacing with Amazon Web Services through Fabric.
Home-page: https://github.com/beanbaginc/fabazon
Maintainer: Christian Hammond
Maintainer-email: christian@beanbaginc.com
License: MIT
Platform: UNKNOWN
Classifier: Development Status :: 3 - Alpha
Classifier: Environment :: Other Environment
Classifier: Intended Audience :: Developers
Classifier: License :: OSI Approved :: MIT License
Classifier: Operating System :: OS Independent
Classifier: Programming Language :: Python
Classifier: Topic :: Software Development
Classifier: Topic :: Software Development :: Libraries :: Python Modules
Requires-Dist: boto (>=2.36)
Requires-Dist: boto3
Requires-Dist: fabric (>=1.8)
